dagster_toolbox/__init__.py
dagster_toolbox/functions/__init__.py
dagster_toolbox/functions/dataframe.py
dagster_toolbox/functions/ftp.py
dagster_toolbox/functions/google_analytics.py
dagster_toolbox/functions/partitions.py
dagster_toolbox/functions/sftp.py
dagster_toolbox/functions/text.py
dagster_toolbox/resources/__init__.py
dagster_toolbox/resources/abstract.py
dagster_toolbox/resources/csv_partitioned_io_manager.py
dagster_toolbox/resources/json_partitioned_io_manager.py
dagster_toolbox/resources/postgres_io_manager.py
dagster_toolbox/resources/postgres_partitioned_io_manager.py
dagster_toolbox/resources/vault.py
dagster_toolbox/types/__init__.py
dagster_toolbox/types/common/__init__.py
dagster_toolbox/types/common/cities.py
dagster_toolbox/types/common/continents.py
dagster_toolbox/types/common/countries.py
dagster_toolbox/types/common/postcodes.py
dagster_toolbox/types/common/regions.py
dagster_toolbox/types/common/subregions.py
dagster_toolbox/types/datahub/__init__.py
dagster_toolbox/types/datahub/container_codes.py
dagster_toolbox/types/datahub/continent_codes.py
dagster_toolbox/types/datahub/country_codes.py
dagster_toolbox/types/datahub/currency_codes.py
dagster_toolbox/types/datahub/language_codes.py
dagster_toolbox/types/datahub/subdivision_codes.py
dagster_toolbox/types/datahub/units_of_measure.py
dagster_toolbox/types/geonames/__init__.py
dagster_toolbox/types/geonames/postal_codes.py
dagster_toolbox/types/google_analytics/__init__.py
dagster_toolbox/types/google_analytics/google_analytics.py
dagster_toolbox/types/open_data_fr/__init__.py
dagster_toolbox/types/open_data_fr/agriculture_ministry.py
dagster_toolbox-0.0.23.dist-info/LICENSE
dagster_toolbox-0.0.23.dist-info/METADATA
dagster_toolbox-0.0.23.dist-info/WHEEL
dagster_toolbox-0.0.23.dist-info/top_level.txt
dagster_toolbox-0.0.23.dist-info/RECORD
