Metadata-Version: 2.1
Name: dagster-toolbox
Version: 0.0.23
Summary: A set of tools to ease Dagster usage
Home-page: https://nicolasramy.github.io/dagster-toolbox/
Author: Nicolas RAMY
Author-email: nicolas.ramy@darkelda.com
License: MIT
Classifier: Development Status :: 3 - Alpha
Classifier: License :: OSI Approved :: MIT License
Classifier: Operating System :: OS Independent
Classifier: Programming Language :: Python :: 3.10
Classifier: Topic :: Terminals
Classifier: Topic :: Utilities
License-File: LICENSE
Requires-Dist: dagster ==1.8.4
Requires-Dist: dagster-aws ==0.24.4
Requires-Dist: dagster-pandas ==0.24.4
Requires-Dist: dagster-pandera ==0.24.4
Requires-Dist: dagster-postgres ==0.24.4
Requires-Dist: google-api-python-client ==2.143.0
Requires-Dist: hvac ==2.3.0
Requires-Dist: minio ==7.2.8
Requires-Dist: oauth2client ==4.1.3
Requires-Dist: pandas ==2.2.2
Requires-Dist: python-slugify ==8.0.4
Requires-Dist: requests ==2.32.3
Requires-Dist: SQLAlchemy ==2.0.32
